Metadata-Version: 2.1
Name: pnomo
Version: 0.0.1
Summary: This is a bookmark!
Home-page: https://github.com/patod01/beta-beam
Author: Patricio C. V. - patod01
Author-email: patod01@telegmail.com
License: WTFPL
Platform: windous
Classifier: License :: Freeware
Classifier: Operating System :: Microsoft :: Windows :: Windows 10
Classifier: Programming Language :: Python :: 3.9
Requires-Python: >=3.9
Provides-Extra: asdf
